lz4-4.4.3.dist-info/RECORD
lz4-4.4.3.dist-info/LICENSE
lz4-4.4.3.dist-info/WHEEL
lz4-4.4.3.dist-info/top_level.txt
lz4-4.4.3.dist-info/METADATA
lz4/version.py
lz4/__init__.py
lz4/_version.cpython-313-darwin.so
lz4/frame/__init__.py
lz4/frame/_frame.cpython-313-darwin.so
lz4/block/_block.cpython-313-darwin.so
lz4/block/__init__.py
